README.rst
setup.cfg
setup.py
taskman/__init__.py
taskman/queue.py
taskman.egg-info/PKG-INFO
taskman.egg-info/SOURCES.txt
taskman.egg-info/dependency_links.txt
taskman.egg-info/requires.txt
taskman.egg-info/top_level.txt