Metadata-Version: 1.1
Name: taskman
Version: 0.0.5
Summary: A python task manager using Consul for its backend.
Home-page: http://github.com/billyshambrook/taskman
Author: Billy Shambrook
Author-email: billy.shambrook@gmail.com
License: BSD
Keywords: task,manager,consul,queue,worker
Platform: UNKNOWN
Classifier: Development Status :: 2 - Pre-Alpha
Classifier: Intended Audience :: Developers
Classifier: License :: OSI Approved :: BSD License
Classifier: Operating System :: Unix
Classifier: Operating System :: POSIX
Classifier: Operating System :: Microsoft :: Windows
Classifier: Programming Language :: Python
Classifier: Programming Language :: Python :: 2
Classifier: Programming Language :: Python :: 2.7
Classifier: Programming Language :: Python :: 3
Classifier: Programming Language :: Python :: 3.4
Classifier: Programming Language :: Python :: 3.5
Classifier: Topic :: Utilities
